dkpro_cassis_tools/__init__.py
dkpro_cassis_tools/create_cas_from_sentences.py
dkpro_cassis_tools/dump_cas_to_zip_file.py
dkpro_cassis_tools/get_document_meta_data.py
dkpro_cassis_tools/load_cas_from_zip_file.py
dkpro_cassis_tools/ns.py
dkpro_cassis_tools/restore_cas_segmentation_by_newline.py
dkpro_cassis_tools/tokenize_cas.py
tests/__init__.py
tests/test_create_cas_from_sentences.py
tests/test_dump_cas_to_zip_file.py
tests/test_get_document_meta_data.py
tests/test_load_cas_from_zip_file.py
tests/test_restore_cas_segmentation_by_newline.py
tests/test_tokenize_cas.py
dkpro_cassis_tools-0.0.6.dist-info/METADATA
dkpro_cassis_tools-0.0.6.dist-info/WHEEL
dkpro_cassis_tools-0.0.6.dist-info/top_level.txt
dkpro_cassis_tools-0.0.6.dist-info/RECORD
