Metadata-Version: 2.1
Name: dkpro-cassis-tools
Version: 0.0.6
Summary: Tools for dkpro cassis
Home-page: https://github.com/pangeamt/dkpro_cassis_tools
Author: Laurent Bié
Author-email: l.bie@pangeanic.com  
License: UNKNOWN
Platform: UNKNOWN
Classifier: Programming Language :: Python :: 3
Classifier: License :: OSI Approved :: MIT License
Classifier: Operating System :: OS Independent
Requires-Python: >=3.7
Requires-Dist: dkpro-cassis (>=0.5.0)
Requires-Dist: sequence-transfer (>=0.1.0)
